{
  "name": "slack-channelinfo-get",
  "version": "v3",
  "createdAt": "Wed Jan 25 2017 17:52:54 GMT+0530 (IST)",
  "errors": [
    {
      "message": "type object should have displayTitle key.",
      "path": []
    },
    {
      "message": "type boolean should have 'displayTitle' key.",
      "path": [
        "properties",
        "channels",
        "items",
        "properties",
        "is_im"
      ]
    },
    {
      "message": "type boolean should have 'displayTitle' key.",
      "path": [
        "properties",
        "channels",
        "items",
        "properties",
        "is_user_deleted"
      ]
    },
    {
      "message": "type string should have 'displayTitle' key.",
      "path": [
        "properties",
        "channels",
        "items",
        "properties",
        "topic",
        "properties",
        "creator"
      ]
    }
  ]
}